koda/__init__.py
koda/_cruft.py
koda/_generics.py
koda/either.py
koda/maybe.py
koda/py.typed
koda/result.py
koda/utils.py
koda-1.4.0.dist-info/LICENSE
koda-1.4.0.dist-info/WHEEL
koda-1.4.0.dist-info/METADATA
koda-1.4.0.dist-info/RECORD
