Metadata-Version: 2.1
Name: koda
Version: 1.4.0
Summary: Type-safe functional tools for Python
Home-page: https://github.com/keithasaurus/koda
License: MIT
Keywords: functional programming,type hints
Author: Keith Philpott
Requires-Python: >=3.8,<4.0
Classifier: License :: OSI Approved :: MIT License
Classifier: Programming Language :: Python :: 3
Classifier: Programming Language :: Python :: 3.8
Classifier: Programming Language :: Python :: 3.9
Classifier: Programming Language :: Python :: 3.10
Classifier: Programming Language :: Python :: 3.11
